MANIFEST.in
README.rst
VERSION
requirement.txt
setup.py
pypostelium/__init__.py
pypostelium/pypostelium.py
pypostelium.egg-info/PKG-INFO
pypostelium.egg-info/SOURCES.txt
pypostelium.egg-info/dependency_links.txt
pypostelium.egg-info/not-zip-safe
pypostelium.egg-info/requires.txt
pypostelium.egg-info/top_level.txt