Metadata-Version: 1.1
Name: pypostelium
Version: 0.0.4
Summary: Python library for supporting Point of Sale payment terminal with Concert protocol
Home-page: https://github.com/akretion/pypostelium
Author: Akretion
Author-email: contact@akretion.com
License: AGPLv3+
Keywords: Concert Telium payment terminal
Platform: UNKNOWN
Classifier: Development Status :: 5 - Production/Stable
Classifier: Intended Audience :: Developers
Classifier: Topic :: Software Development :: User Interfaces
Classifier: License :: OSI Approved :: GNU Affero General Public License v3
Classifier: Programming Language :: Python :: 2.7
Classifier: Programming Language :: Python :: 3.8
